django_htmx_ui/__init__.py
django_htmx_ui/admin.py
django_htmx_ui/apps.py
django_htmx_ui/forms.py
django_htmx_ui/jinja.py
django_htmx_ui/middleware.py
django_htmx_ui/models.py
django_htmx_ui/tests.py
django_htmx_ui/urls.py
django_htmx_ui/utils.py
django_htmx_ui/migrations/__init__.py
django_htmx_ui/views/crud.py
django_htmx_ui/views/generic.py
django_htmx_ui/views/mixins.py
django_htmx_ui-0.1.8.dist-info/LICENSE
django_htmx_ui-0.1.8.dist-info/METADATA
django_htmx_ui-0.1.8.dist-info/WHEEL
django_htmx_ui-0.1.8.dist-info/top_level.txt
django_htmx_ui-0.1.8.dist-info/RECORD
